check_constraint/__init__.py
check_constraint/apps.py
check_constraint/models.py
check_constraint/tests.py
demo/migrations/0001_initial.py
demo/migrations/0002_auto_20200218_0733.py
demo/migrations/0003_auto_20200222_0146.py
demo/migrations/__init__.py
demo/models/__init__.py
demo/models/book.py
demo/models/library.py
demo/models/function/__init__.py
demo/models/function/non_null_count.py
django_check_constraint/__init__.py
django_check_constraint/settings.py
django_check_constraint/urls.py
django_check_constraint/wsgi.py
django_check_constraint-1.0.18.dist-info/LICENSE
django_check_constraint-1.0.18.dist-info/METADATA
django_check_constraint-1.0.18.dist-info/WHEEL
django_check_constraint-1.0.18.dist-info/top_level.txt
django_check_constraint-1.0.18.dist-info/RECORD
