Metadata-Version: 2.1
Name: django-check-constraint
Version: 1.0.18
Summary: Extends django check constraint to support annotations.
Home-page: https://github.com/jackton1/django-check-constraint
Author: Tonye Jack
Author-email: jtonye@ymail.com
Maintainer: Tonye Jack
Maintainer-email: jtonye@ymail.com
License: MIT/Apache-2.0
Keywords: django,django-check-constraint,django check constraint,check constraint-django,model constraints
Platform: UNKNOWN
Classifier: Development Status :: 3 - Alpha
Classifier: Intended Audience :: Developers
Classifier: License :: OSI Approved :: MIT License
Classifier: License :: OSI Approved :: Apache Software License
Classifier: Natural Language :: English
Classifier: Topic :: Internet :: WWW/HTTP
Classifier: Operating System :: OS Independent
Classifier: Programming Language :: Python :: 3.5
Classifier: Programming Language :: Python :: 3.6
Classifier: Programming Language :: Python :: 3.7
Classifier: Programming Language :: Python :: 3.8
Classifier: Programming Language :: Python :: Implementation :: CPython
Classifier: Programming Language :: Python :: Implementation :: PyPy
Classifier: Framework :: Django :: 2.2
Classifier: Framework :: Django :: 3.0
Requires-Python: >=3.5
Requires-Dist: Django (>=2.2.10)
Provides-Extra: deploy
Requires-Dist: bump2version (==1.0.0) ; extra == 'deploy'
Requires-Dist: readme-renderer[md] ; extra == 'deploy'
Requires-Dist: changes (==0.7.0) ; extra == 'deploy'
Requires-Dist: git-changelog (==0.1.0) ; extra == 'deploy'
Requires-Dist: twine (==1.3.1) ; extra == 'deploy'
Provides-Extra: development
Requires-Dist: pip-tools (==4.4.1) ; extra == 'development'
Requires-Dist: check-manifest (==0.37) ; extra == 'development'
Requires-Dist: psycopg2 (>=2.5.4) ; extra == 'development'
Requires-Dist: mysqlclient (>=1.3.13) ; extra == 'development'
Requires-Dist: Django (>=2.2.10) ; extra == 'development'
Requires-Dist: nox (==2019.11.9) ; extra == 'development'
Requires-Dist: pluggy (>=0.7) ; extra == 'development'
Requires-Dist: mock (==2.0.0) ; extra == 'development'
Requires-Dist: unittest-xml-reporting (==2.5.2) ; extra == 'development'
Requires-Dist: codacy-coverage (==1.3.11) ; extra == 'development'
Requires-Dist: flake8 (==3.4.1) ; extra == 'development'
Requires-Dist: yamllint (==1.10.0) ; extra == 'development'
Requires-Dist: isort (==4.2.15) ; extra == 'development'
Requires-Dist: pre-commit (==2.0.1) ; extra == 'development'
Provides-Extra: lint
Requires-Dist: flake8 (==3.4.1) ; extra == 'lint'
Requires-Dist: yamllint (==1.10.0) ; extra == 'lint'
Requires-Dist: isort (==4.2.15) ; extra == 'lint'
Requires-Dist: pre-commit (==2.0.1) ; extra == 'lint'
Provides-Extra: nox
Requires-Dist: nox (==2019.11.9) ; extra == 'nox'
Requires-Dist: pluggy (>=0.7) ; extra == 'nox'
Requires-Dist: mock (==2.0.0) ; extra == 'nox'
Requires-Dist: unittest-xml-reporting (==2.5.2) ; extra == 'nox'
Requires-Dist: codacy-coverage (==1.3.11) ; extra == 'nox'
Provides-Extra: test
Requires-Dist: nox (==2019.11.9) ; extra == 'test'
Requires-Dist: pluggy (>=0.7) ; extra == 'test'
Requires-Dist: mock (==2.0.0) ; extra == 'test'
Requires-Dist: unittest-xml-reporting (==2.5.2) ; extra == 'test'
Requires-Dist: codacy-coverage (==1.3.11) ; extra == 'test'
